beebee/__init__.py
beebee/convert_entsoe_to_numpy.py
beebee-0.3.dist-info/LICENSE
beebee-0.3.dist-info/METADATA
beebee-0.3.dist-info/WHEEL
beebee-0.3.dist-info/entry_points.txt
beebee-0.3.dist-info/top_level.txt
beebee-0.3.dist-info/RECORD
