Metadata-Version: 2.1
Name: beebee
Version: 0.3
Summary: Process RDF data for use in Brightway2
Home-page: https://github.com/BONSAMURAIS/beebee
Author: Chris Mutel
Author-email: cmutel@gmail.com
License: BSD 3-Clause License
Requires-Dist: docopt
Requires-Dist: numpy
Requires-Dist: arborist
Requires-Dist: bentso
